evmutation2/__about__.py
evmutation2/__init__.py
evmutation2/data.py
evmutation2/ema.py
evmutation2/features.py
evmutation2/main.py
evmutation2/model.py
evmutation2/parsers.py
evmutation2/rigid_utils.py
evmutation2/structures.py
evmutation2/utils.py
evmutation2/alphafold3_pytorch/__init__.py
evmutation2/alphafold3_pytorch/alphafold3.py
evmutation2/alphafold3_pytorch/attention.py
evmutation2/alphafold3_pytorch/model_utils.py
evmutation2/alphafold3_pytorch/tensor_typing.py
evmutation2/alphafold3_pytorch/utils.py
evmutation2/scripts/__init__.py
evmutation2/scripts/create_alignment_db_from_zip.py
evmutation2/scripts/create_alignment_db_sharded.py
evmutation2/scripts/create_file_db.py
evmutation2/scripts/merge_index.py
evmutation2-0.0.1.dist-info/METADATA
evmutation2-0.0.1.dist-info/WHEEL
evmutation2-0.0.1.dist-info/licenses/LICENSE.txt
evmutation2-0.0.1.dist-info/RECORD
