Metadata-Version: 2.4
Name: evmutation2
Version: 0.0.1
Project-URL: Documentation, https://github.com/thomashopf/evmutation2#readme
Project-URL: Issues, https://github.com/thomashopf/evmutation2/issues
Project-URL: Source, https://github.com/thomashopf/evmutation2
Author-email: Thomas Hopf <thomas.hopf@gmail.com>
License-Expression: MIT
License-File: LICENSE.txt
Classifier: Development Status :: 4 - Beta
Classifier: Programming Language :: Python
Classifier: Programming Language :: Python :: 3.12
Classifier: Programming Language :: Python :: Implementation :: CPython
Requires-Python: >=3.12
Requires-Dist: beartype
Requires-Dist: biopython>=1.84
Requires-Dist: click
Requires-Dist: einops
Requires-Dist: einx
Requires-Dist: environs
Requires-Dist: jaxtyping
Requires-Dist: jsonargparse[signatures]
Requires-Dist: lightning
Requires-Dist: loguru
Requires-Dist: msgpack
Requires-Dist: numpy
Requires-Dist: pandas
Requires-Dist: pyarrow
Requires-Dist: requests
Requires-Dist: torch
Requires-Dist: torchdata
